{".class": "MypyFile", "_fullname": "purchase_model", "is_partial_stub_package": false, "is_stub": false, "names": {".class": "SymbolTable", "OrderSupplier": {".class": "SymbolTableNode", "kind": "Gdef", "node": {".class": "Var", "flags": ["is_suppressed_import", "is_ready"], "fullname": "purchase_model.OrderSupplier", "name": "OrderSupplier", "type": {".class": "AnyType", "missing_import_name": "purchase_model.OrderSupplier", "source_any": null, "type_of_any": 3}}}, "Purchase": {".class": "SymbolTableNode", "kind": "Gdef", "node": {".class": "TypeInfo", "_promote": null, "abstract_attributes": [], "bases": ["builtins.object"], "declared_metaclass": null, "defn": {".class": "ClassDef", "fullname": "purchase_model.Purchase", "name": "Purchase", "type_vars": []}, "flags": ["fallback_to_any"], "fullname": "purchase_model.Purchase", "metaclass_type": null, "metadata": {}, "module_name": "purchase_model", "mro": ["purchase_model.Purchase", "builtins.object"], "names": {".class": "SymbolTable", "date": {".class": "SymbolTableNode", "kind": "Mdef", "node": {".class": "Var", "flags": ["is_initialized_in_class"], "fullname": "purchase_model.Purchase.date", "name": "date", "type": {".class": "AnyType", "missing_import_name": "app.SQLAlchemy", "source_any": {".class": "AnyType", "missing_import_name": "app.SQLAlchemy", "source_any": null, "type_of_any": 3}, "type_of_any": 7}}}, "from_dict": {".class": "SymbolTableNode", "kind": "Mdef", "node": {".class": "FuncDef", "arg_kinds": [0, 0, 0], "arg_names": ["self", "data", "supplier"], "flags": [], "fullname": "purchase_model.Purchase.from_dict", "name": "from_dict", "type": null}}, "id": {".class": "SymbolTableNode", "kind": "Mdef", "node": {".class": "Var", "flags": ["is_initialized_in_class"], "fullname": "purchase_model.Purchase.id", "name": "id", "type": {".class": "AnyType", "missing_import_name": "app.SQLAlchemy", "source_any": {".class": "AnyType", "missing_import_name": "app.SQLAlchemy", "source_any": null, "type_of_any": 3}, "type_of_any": 7}}}, "orders_supplier": {".class": "SymbolTableNode", "kind": "Mdef", "node": {".class": "Var", "flags": ["is_initialized_in_class"], "fullname": "purchase_model.Purchase.orders_supplier", "name": "orders_supplier", "type": {".class": "AnyType", "missing_import_name": "app.SQLAlchemy", "source_any": {".class": "AnyType", "missing_import_name": "app.SQLAlchemy", "source_any": null, "type_of_any": 3}, "type_of_any": 7}}}, "paid": {".class": "SymbolTableNode", "kind": "Mdef", "node": {".class": "Var", "flags": ["is_initialized_in_class"], "fullname": "purchase_model.Purchase.paid", "name": "paid", "type": {".class": "AnyType", "missing_import_name": "app.SQLAlchemy", "source_any": {".class": "AnyType", "missing_import_name": "app.SQLAlchemy", "source_any": null, "type_of_any": 3}, "type_of_any": 7}}}, "supplier": {".class": "SymbolTableNode", "implicit": true, "kind": "Mdef", "node": {".class": "Var", "flags": [], "fullname": "purchase_model.Purchase.supplier", "name": "supplier", "type": {".class": "AnyType", "missing_import_name": null, "source_any": null, "type_of_any": 1}}}, "supplier_id": {".class": "SymbolTableNode", "kind": "Mdef", "node": {".class": "Var", "flags": ["is_initialized_in_class"], "fullname": "purchase_model.Purchase.supplier_id", "name": "supplier_id", "type": {".class": "AnyType", "missing_import_name": "app.SQLAlchemy", "source_any": {".class": "AnyType", "missing_import_name": "app.SQLAlchemy", "source_any": null, "type_of_any": 3}, "type_of_any": 7}}}, "taxes_included": {".class": "SymbolTableNode", "kind": "Mdef", "node": {".class": "Var", "flags": ["is_initialized_in_class"], "fullname": "purchase_model.Purchase.taxes_included", "name": "taxes_included", "type": {".class": "AnyType", "missing_import_name": "app.SQLAlchemy", "source_any": {".class": "AnyType", "missing_import_name": "app.SQLAlchemy", "source_any": null, "type_of_any": 3}, "type_of_any": 7}}}, "to_dict": {".class": "SymbolTableNode", "kind": "Mdef", "node": {".class": "FuncDef", "arg_kinds": [0], "arg_names": ["self"], "flags": [], "fullname": "purchase_model.Purchase.to_dict", "name": "to_dict", "type": null}}, "total_price": {".class": "SymbolTableNode", "kind": "Mdef", "node": {".class": "Var", "flags": ["is_initialized_in_class"], "fullname": "purchase_model.Purchase.total_price", "name": "total_price", "type": {".class": "AnyType", "missing_import_name": "app.SQLAlchemy", "source_any": {".class": "AnyType", "missing_import_name": "app.SQLAlchemy", "source_any": null, "type_of_any": 3}, "type_of_any": 7}}}}, "tuple_type": null, "type_vars": [], "typeddict_type": null}}, "__doc__": {".class": "SymbolTableNode", "kind": "Gdef", "node": {".class": "Var", "flags": ["is_ready"], "fullname": "purchase_model.__doc__", "name": "__doc__", "type": "builtins.str"}}, "__file__": {".class": "SymbolTableNode", "kind": "Gdef", "node": {".class": "Var", "flags": ["is_ready"], "fullname": "purchase_model.__file__", "name": "__file__", "type": "builtins.str"}}, "__name__": {".class": "SymbolTableNode", "kind": "Gdef", "node": {".class": "Var", "flags": ["is_ready"], "fullname": "purchase_model.__name__", "name": "__name__", "type": "builtins.str"}}, "__package__": {".class": "SymbolTableNode", "kind": "Gdef", "node": {".class": "Var", "flags": ["is_ready"], "fullname": "purchase_model.__package__", "name": "__package__", "type": "builtins.str"}}, "current_app": {".class": "SymbolTableNode", "cross_ref": "flask.globals.current_app", "kind": "Gdef"}, "datetime": {".class": "SymbolTableNode", "cross_ref": "datetime.datetime", "kind": "Gdef"}, "db": {".class": "SymbolTableNode", "cross_ref": "app.db", "kind": "Gdef"}, "md5": {".class": "SymbolTableNode", "cross_ref": "hashlib.md5", "kind": "Gdef"}, "time": {".class": "SymbolTableNode", "cross_ref": "time.time", "kind": "Gdef"}, "timedelta": {".class": "SymbolTableNode", "cross_ref": "datetime.timedelta", "kind": "Gdef"}}, "path": "c:\\Users\\Michael\\OneDrive\\Desktop\\fam_backend\\app\\models\\purchase_model.py"}